[
    {
        "id": 1,
        "title": "Halloween makeup 😈",
        "date": "27.10.2018",
        "text": "23 октября в 14.00 по адресу ул. Ленинская 23а пройдёт мой Мастер-класс на тему \"Halloween makeup\" 😈\n        Запись на МК в директ или по телефону +375296916958 WhatsApp Viber",
        "imagePath": "https://pp.userapi.com/c850124/v850124946/4d687/qkxQKfoiCsw.jpg"
    },
    {
        "id": 2,
        "title": "Собирали на фотосесс,ию Unreal @viktoryia.raynes ",
        "date": "27.10.2018",
        "text": "Собирали на фотосессию Unreal @viktoryia.raynes 😍 мой макияж для красотки Вики, \n        обалденные локоны от @gapeevakate 💜 Стильные серьги @bijuteri_mog 💙 Ждём не менее \n        крутых фото от @pyzhovds в обалденно-красном платье от @studia_prokata_mogilev 💕",
        "imagePath": "https://pp.userapi.com/c844321/v844321794/108523/3YpzBi8kUac.jpg"
    },
    {
        "id": 3,
        "title": "Halloween makeup 😈",
        "date": "27.10.2018",
        "text": "23 октября в 14.00 по адресу ул. Ленинская 23а пройдёт мой Мастер-класс на тему \"Halloween makeup\" 😈\n        Запись на МК в директ или по телефону +375296916958 WhatsApp Viber",
        "imagePath": "https://pp.userapi.com/c850124/v850124946/4d687/qkxQKfoiCsw.jpg"
    },
    {
        "id": 4,
        "title": "Halloween makeup 😈",
        "date": "27.10.2018",
        "text": "23 октября в 14.00 по адресу ул. Ленинская 23а пройдёт мой Мастер-класс на тему \"Halloween makeup\" 😈\n        Запись на МК в директ или по телефону +375296916958 WhatsApp Viber",
        "imagePath": "https://pp.userapi.com/c850124/v850124946/4d687/qkxQKfoiCsw.jpg"
    }
]